setup.py
pub/__init__.py
pub/pub.py
pub.egg-info/PKG-INFO
pub.egg-info/SOURCES.txt
pub.egg-info/dependency_links.txt
pub.egg-info/requires.txt
pub.egg-info/top_level.txt
pub/bin/pub
pub/shortcuts/__init__.py
pub/shortcuts/shortcuts.py
test/test_deps.py
test/test_pub.py
test/test_task.py