Metadata-Version: 1.0
Name: pub
Version: 0.0.2
Summary: Python Utility Belt
Home-page: https://github.com/llimllib/pub
Author: Bill Mill
Author-email: bill.mill@gmail.com
License: MIT
Platform: UNKNOWN
Classifier: Development Status :: 2 - Pre-Alpha
Classifier: Intended Audience :: Developers
Classifier: Natural Language :: English
Classifier: License :: OSI Approved :: MIT License
Classifier: Programming Language :: Python
Classifier: Programming Language :: Python :: 2.6
Classifier: Programming Language :: Python :: 2.7
